Workbook

Sheet Como usar
B2: Planilha de precificação de obras e serviços
B3: Rogério Vieira · Engenharia — calcule custo, BDI e preço de venda
B5: COMO FUNCIONA
B6: 1. Parâmetros: confira as diárias da equipe, os encargos e os itens do BDI (lucro, administração, impostos…).
B7: 2. Insumos: atualize os preços dos materiais (os da cidade/do seu fornecedor). A mão de obra é calculada sozinha a partir das diárias.
B8: 3. Composições: mostra quanto cada serviço gasta de material e de horas por unidade (m², un…). Ajuste os coeficientes com a sua experiência.
B9: 4. Serviços: custo direto e preço de venda (com BDI) de cada serviço, calculados automaticamente.
B10: 5. Orçamento: escolha o serviço na lista, digite a quantidade e o preço final aparece. Use para montar o orçamento da obra.
B11: 6. Estimativa m²: conta rápida para construção e reforma pela área, antes do orçamento detalhado.
B13: CORES
B14: Texto AZUL com fundo AMARELO = campo para você preencher ou ajustar.
B15: Texto preto = fórmula (calcula sozinho, não precisa mexer).
... B22: Exemplo de campo para preencher: 180,00

Sheet Orçamento
A1: Orçamento da obra
A2: Escolha o código do serviço, digite a quantidade — o preço aparece sozinho
A3: Obra / cliente: | C3: Ex.: Reforma E.E. Exemplo
A5: Item | B5: Código | C5: Serviço | D5: Unid. | E5: Quantidade | F5: Custo unit. (R$) | G5: Custo total (R$) | H5: Preço unit. (R$) | I5: Preço total (R$)
A6: 1 | B6: S02 | C6: =IF(B6="","",IFERROR(INDEX('Serviços'!$B$5:$B$44,MATCH(B6,'Serviços'!$A$5:$A$44,0)),"código não encontrado")) | D6: =IF(B6="","",IFERROR(INDEX('Serviços'!$C$5:$C$44,MATCH(B6,'Serviços'!$A$5:$A$44,0)),"")) | E6: 120 | F6: =IF(B6="",0,IFERROR(INDEX('Serviços'!$F$5:$F$44,MATCH(B6,'Serviços'!$A$5:$A$44,0)),0)) | G6: =E6*F6 | H6: =F6*(1+'Parâmetros'!$B$31) | I6: =E6*H6
A7: 2 | B7: S03 | C7: =IF(B7="","",IFERROR(INDEX('Serviços'!$B$5:$B$44,MATCH(B7,'Serviços'!$A$5:$A$44,0)),"código não encontrado")) | D7: =IF(B7="","",IFERROR(INDEX('Serviços'!$C$5:$C$44,MATCH(B7,'Serviços'!$A$5:$A$44,0)),"")) | E7: 120 | F7: =IF(B7="",0,IFERROR(INDEX('Serviços'!$F$5:$F$44,MATCH(B7,'Serviços'!$A$5:$A$44,0)),0)) | G7: =E7*F7 | H7: =F7*(1+'Parâmetros'!$B$31) | I7: =E7*H7
A8: 3 | B8: S06 | C8: =IF(B8="","",IFERROR(INDEX('Serviços'!$B$5:$B$44,MATCH(B8,'Serviços'!$A$5:$A$44,0)),"código não encontrado")) | D8: =IF(B8="","",IFERROR(INDEX('Serviços'!$C$5:$C$44,MATCH(B8,'Serviços'!$A$5:$A$44,0)),"")) | E8: 350 | F8: =IF(B8="",0,IFERROR(INDEX('Serviços'!$F$5:$F$44,MATCH(B8,'Serviços'!$A$5:$A$44,0)),0)) | G8: =E8*F8 | H8: =F8*(1+'Parâmetros'!$B$31) | I8: =E8*H8
A9: 4 | B9: S07 | C9: =IF(B9="","",IFERROR(INDEX('Serviços'!$B$5:$B$44,MATCH(B9,'Serviços'!$A$5:$A$44,0)),"código não encontrado")) | D9: =IF(B9="","",IFERROR(INDEX('Serviços'!$C$5:$C$44,MATCH(B9,'Serviços'!$A$5:$A$44,0)),"")) | E9: 6 | F9: =IF(B9="",0,IFERROR(INDEX('Serviços'!$F$5:$F$44,MATCH(B9,'Serviços'!$A$5:$A$44,0)),0)) | G9: =E9*F9 | H9: =F9*(1+'Parâmetros'!$B$31) | I9: =E9*H9
A10: 5 | B10: S08 | C10: =IF(B10="","",IFERROR(INDEX('Serviços'!$B$5:$B$44,MATCH(B10,'Serviços'!$A$5:$A$44,0)),"código não encontrado")) | D10: =IF(B10="","",IFERROR(INDEX('Serviços'!$C$5:$C$44,MATCH(B10,'Serviços'!$A$5:$A$44,0)),"")) | E10: 40 | F10: =IF(B10="",0,IFERROR(INDEX('Serviços'!$F$5:$F$44,MATCH(B10,'Serviços'!$A$5:$A$44,0)),0)) | G10: =E10*F10 | H10: =F10*(1+'Parâmetros'!$B$31) | I10: =E10*H10
A11: 6 | C11: =IF(B11="","",IFERROR(INDEX('Serviços'!$B$5:$B$44,MATCH(B11,'Serviços'!$A$5:$A$44,0)),"código não encontrado")) | D11: =IF(B11="","",IFERROR(INDEX('Serviços'!$C$5:$C$44,MATCH(B11,'Serviços'!$A$5:$A$44,0)),"")) | F11: =IF(B11="",0,IFERROR(INDEX('Serviços'!$F$5:$F$44,MATCH(B11,'Serviços'!$A$5:$A$44,0)),0)) | G11: =E11*F11 | H11: =F11*(1+'Parâmetros'!$B$31) | I11: =E11*H11
A12: 7 | C12: =IF(B12="","",IFERROR(INDEX('Serviços'!$B$5:$B$44,MATCH(B12,'Serviços'!$A$5:$A$44,0)),"código não encontrado")) | D12: =IF(B12="","",IFERROR(INDEX('Serviços'!$C$5:$C$44,MATCH(B12,'Serviços'!$A$5:$A$44,0)),"")) | F12: =IF(B12="",0,IFERROR(INDEX('Serviços'!$F$5:$F$44,MATCH(B12,'Serviços'!$A$5:$A$44,0)),0)) | G12: =E12*F12 | H12: =F12*(1+'Parâmetros'!$B$31) | I12: =E12*H12
A13: 8 | C13: =IF(B13="","",IFERROR(INDEX('Serviços'!$B$5:$B$44,MATCH(B13,'Serviços'!$A$5:$A$44,0)),"código não encontrado")) | D13: =IF(B13="","",IFERROR(INDEX('Serviços'!$C$5:$C$44,MATCH(B13,'Serviços'!$A$5:$A$44,0)),"")) | F13: =IF(B13="",0,IFERROR(INDEX('Serviços'!$F$5:$F$44,MATCH(B13,'Serviços'!$A$5:$A$44,0)),0)) | G13: =E13*F13 | H13: =F13*(1+'Parâmetros'!$B$31) | I13: =E13*H13
A14: 9 | C14: =IF(B14="","",IFERROR(INDEX('Serviços'!$B$5:$B$44,MATCH(B14,'Serviços'!$A$5:$A$44,0)),"código não encontrado")) | D14: =IF(B14="","",IFERROR(INDEX('Serviços'!$C$5:$C$44,MATCH(B14,'Serviços'!$A$5:$A$44,0)),"")) | F14: =IF(B14="",0,IFERROR(INDEX('Serviços'!$F$5:$F$44,MATCH(B14,'Serviços'!$A$5:$A$44,0)),0)) | G14: =E14*F14 | H14: =F14*(1+'Parâmetros'!$B$31) | I14: =E14*H14
A15: 10 | C15: =IF(B15="","",IFERROR(INDEX('Serviços'!$B$5:$B$44,MATCH(B15,'Serviços'!$A$5:$A$44,0)),"código não encontrado")) | D15: =IF(B15="","",IFERROR(INDEX('Serviços'!$C$5:$C$44,MATCH(B15,'Serviços'!$A$5:$A$44,0)),"")) | F15: =IF(B15="",0,IFERROR(INDEX('Serviços'!$F$5:$F$44,MATCH(B15,'Serviços'!$A$5:$A$44,0)),0)) | G15: =E15*F15 | H15: =F15*(1+'Parâmetros'!$B$31) | I15: =E15*H15
A16: 11 | C16: =IF(B16="","",IFERROR(INDEX('Serviços'!$B$5:$B$44,MATCH(B16,'Serviços'!$A$5:$A$44,0)),"código não encontrado")) | D16: =IF(B16="","",IFERROR(INDEX('Serviços'!$C$5:$C$44,MATCH(B16,'Serviços'!$A$5:$A$44,0)),"")) | F16: =IF(B16="",0,IFERROR(INDEX('Serviços'!$F$5:$F$44,MATCH(B16,'Serviços'!$A$5:$A$44,0)),0)) | G16: =E16*F16 | H16: =F16*(1+'Parâmetros'!$B$31) | I16: =E16*H16
A17: 12 | C17: =IF(B17="","",IFERROR(INDEX('Serviços'!$B$5:$B$44,MATCH(B17,'Serviços'!$A$5:$A$44,0)),"código não encontrado")) | D17: =IF(B17="","",IFERROR(INDEX('Serviços'!$C$5:$C$44,MATCH(B17,'Serviços'!$A$5:$A$44,0)),"")) | F17: =IF(B17="",0,IFERROR(INDEX('Serviços'!$F$5:$F$44,MATCH(B17,'Serviços'!$A$5:$A$44,0)),0)) | G17: =E17*F17 | H17: =F17*(1+'Parâmetros'!$B$31) | I17: =E17*H17
A18: 13 | C18: =IF(B18="","",IFERROR(INDEX('Serviços'!$B$5:$B$44,MATCH(B18,'Serviços'!$A$5:$A$44,0)),"código não encontrado")) | D18: =IF(B18="","",IFERROR(INDEX('Serviços'!$C$5:$C$44,MATCH(B18,'Serviços'!$A$5:$A$44,0)),"")) | F18: =IF(B18="",0,IFERROR(INDEX('Serviços'!$F$5:$F$44,MATCH(B18,'Serviços'!$A$5:$A$44,0)),0)) | G18: =E18*F18 | H18: =F18*(1+'Parâmetros'!$B$31) | I18: =E18*H18
A19: 14 | C19: =IF(B19="","",IFERROR(INDEX('Serviços'!$B$5:$B$44,MATCH(B19,'Serviços'!$A$5:$A$44,0)),"código não encontrado")) | D19: =IF(B19="","",IFERROR(INDEX('Serviços'!$C$5:$C$44,MATCH(B19,'Serviços'!$A$5:$A$44,0)),"")) | F19: =IF(B19="",0,IFERROR(INDEX('Serviços'!$F$5:$F$44,MATCH(B19,'Serviços'!$A$5:$A$44,0)),0)) | G19: =E19*F19 | H19: =F19*(1+'Parâmetros'!$B$31) | I19: =E19*H19
A20: 15 | C20: =IF(B20="","",IFERROR(INDEX('Serviços'!$B$5:$B$44,MATCH(B20,'Serviços'!$A$5:$A$44,0)),"código não encontrado")) | D20: =IF(B20="","",IFERROR(INDEX('Serviços'!$C$5:$C$44,MATCH(B20,'Serviços'!$A$5:$A$44,0)),"")) | F20: =IF(B20="",0,IFERROR(INDEX('Serviços'!$F$5:$F$44,MATCH(B20,'Serviços'!$A$5:$A$44,0)),0)) | G20: =E20*F20 | H20: =F20*(1+'Parâmetros'!$B$31) | I20: =E20*H20
A21: 16 | C21: =IF(B21="","",IFERROR(INDEX('Serviços'!$B$5:$B$44,MATCH(B21,'Serviços'!$A$5:$A$44,0)),"código não encontrado")) | D21: =IF(B21="","",IFERROR(INDEX('Serviços'!$C$5:$C$44,MATCH(B21,'Serviços'!$A$5:$A$44,0)),"")) | F21: =IF(B21="",0,IFERROR(INDEX('Serviços'!$F$5:$F$44,MATCH(B21,'Serviços'!$A$5:$A$44,0)),0)) | G21: =E21*F21 | H21: =F21*(1+'Parâmetros'!$B$31) | I21: =E21*H21
A22: 17 | C22: =IF(B22="","",IFERROR(INDEX('Serviços'!$B$5:$B$44,MATCH(B22,'Serviços'!$A$5:$A$44,0)),"código não encontrado")) | D22: =IF(B22="","",IFERROR(INDEX('Serviços'!$C$5:$C$44,MATCH(B22,'Serviços'!$A$5:$A$44,0)),"")) | F22: =IF(B22="",0,IFERROR(INDEX('Serviços'!$F$5:$F$44,MATCH(B22,'Serviços'!$A$5:$A$44,0)),0)) | G22: =E22*F22 | H22: =F22*(1+'Parâmetros'!$B$31) | I22: =E22*H22
... A30: 25 | C30: =IF(B30="","",IFERROR(INDEX('Serviços'!$B$5:$B$44,MATCH(B30,'Serviços'!$A$5:$A$44,0)),"código não encontrado")) | D30: =IF(B30="","",IFERROR(INDEX('Serviços'!$C$5:$C$44,MATCH(B30,'Serviços'!$A$5:$A$44,0)),"")) | F30: =IF(B30="",0,IFERROR(INDEX('Serviços'!$F$5:$F$44,MATCH(B30,'Serviços'!$A$5:$A$44,0)),0)) | G30: =E30*F30 | H30: =F30*(1+'Parâmetros'!$B$31) | I30: =E30*H30
A32: Custos extras da obra (valor fechado)
C33: Mobilização / desmobilização | G33: 800 | I33: =G33*(1+'Parâmetros'!$B$31)
C34: Caçamba de entulho | G34: 1400 | I34: =G34*(1+'Parâmetros'!$B$31)
C35: ART / taxas | G35: 300 | I35: =G35*(1+'Parâmetros'!$B$31)
C36: Limpeza final | G36: 500 | I36: =G36*(1+'Parâmetros'!$B$31)
C37: Outros | G37: 0 | I37: =G37*(1+'Parâmetros'!$B$31)
C39: Custo direto total | G39: =SUM(G6:G30)+SUM(G33:G37)
C40: BDI aplicado | G40: ='Parâmetros'!$B$31
C41: Valor do BDI | G41: =I42-G39
C42: PREÇO DE VENDA | I42: =SUM(I6:I30)+SUM(I33:I37)
C43: Lucro estimado (parcela de lucro do BDI) | G43: =G39*(1+'Parâmetros'!$B$20+'Parâmetros'!$B$21+'Parâmetros'!$B$22)*(1+'Parâmetros'!$B$23)*'Parâmetros'!$B$24
C44: Margem de lucro sobre o preço | G44: =IF(I42=0,0,G43/I42)

Sheet Parâmetros
A1: Parâmetros
A2: Diárias da equipe, encargos e BDI (fórmula do TCU)
A4: Mão de obra | B4: Diária (R$) | C4: Observação
A5: Pedreiro | B5: 180 | C5: valor da diária paga (exemplo)
A6: Servente | B6: 120 | C6: valor da diária paga (exemplo)
A7: Eletricista | B7: 220 | C7: valor da diária paga (exemplo)
A8: Encanador | B8: 200 | C8: valor da diária paga (exemplo)
A9: Pintor | B9: 180 | C9: valor da diária paga (exemplo)
A10: Carpinteiro | B10: 200 | C10: valor da diária paga (exemplo)
A11: Azulejista | B11: 200 | C11: valor da diária paga (exemplo)
A12: Vidraceiro | B12: 200 | C12: valor da diária paga (exemplo)
A13: Mestre de obras | B13: 250 | C13: valor da diária paga (exemplo)
A15: Horas trabalhadas por dia | B15: 8 | C15: jornada usada para achar o custo da hora
A16: Encargos sobre a mão de obra (%) | B16: 0.2 | C16: EPI, alimentação, transporte, encargos; diarista puro ≈ 10–25%, CLT ≈ 70–120%
A18: BDI — Benefícios e Despesas Indiretas
A19: Item do BDI | B19: % | C19: Referência
A20: Administração central (AC) | B20: 0.04 | C20: custos do escritório, contador, veículo… (TCU: 3% a 5,5%)
A21: Seguro + garantia (S+G) | B21: 0.008 | C21: TCU: 0,8% a 1%
A22: Risco (R) | B22: 0.0127 | C22: imprevistos (TCU: 0,97% a 1,27%)
A23: Despesas financeiras (DF) | B23: 0.0123 | C23: custo de esperar o pagamento (TCU: 0,59% a 1,39%)
A24: Lucro (L) | B24: 0.074 | C24: seu lucro (TCU: 6,16% a 8,96%)
A25: Impostos — PIS | B25: 0.0065 | C25: ajuste conforme o regime da empresa
A26: Impostos — COFINS | B26: 0.03 | C26: ajuste conforme o regime da empresa
A27: Impostos — ISS | B27: 0.02 | C27: Santo André: confira a alíquota do serviço
A28: Impostos — CPRB / outros | B28: 0 | C28: use se a empresa pagar (ex.: 4,5%); no Simples, coloque a alíquota efetiva aqui e zere PIS/COFINS/ISS
A30: Total de impostos (I) | B30: =SUM(B25:B28) | C30: soma dos impostos acima
A31: BDI calculado | B31: =((1+$B$20+$B$21+$B$22)*(1+$B$23)*(1+$B$24)/(1-B30))-1 | C31: BDI = [(1+AC+S+G+R)×(1+DF)×(1+L) / (1−I)] − 1 (Acórdão TCU 2622/2013)

Sheet Insumos
A1: Insumos
A2: Preços de materiais (preencha) e custo da hora da equipe (automático)
A4: Insumo | B4: Unidade | C4: Preço unitário (R$) | D4: Observação
A5: Cimento CP-II 50 kg | B5: saco | C5: 38 | D5: preço de exemplo — atualize
A6: Areia média | B6: m³ | C6: 150 | D6: preço de exemplo — atualize
A7: Brita 1 | B7: m³ | C7: 160 | D7: preço de exemplo — atualize
A8: Cal hidratada 20 kg | B8: saco | C8: 18 | D8: preço de exemplo — atualize
A9: Bloco cerâmico 14x19x39 | B9: un | C9: 2.6 | D9: preço de exemplo — atualize
A10: Argamassa colante AC-II 20 kg | B10: saco | C10: 28 | D10: preço de exemplo — atualize
A11: Rejunte 1 kg | B11: kg | C11: 9 | D11: preço de exemplo — atualize
A12: Piso cerâmico | B12: m² | C12: 45 | D12: preço de exemplo — atualize
A13: Tinta acrílica 18 L | B13: lata | C13: 380 | D13: preço de exemplo — atualize
A14: Massa corrida 25 kg | B14: lata | C14: 95 | D14: preço de exemplo — atualize
A15: Lixa | B15: un | C15: 2 | D15: preço de exemplo — atualize
A16: Selador acrílico 18 L | B16: lata | C16: 160 | D16: preço de exemplo — atualize
... A26: Massa de vidraceiro | B26: kg | C26: 12 | D26: preço de exemplo — atualize
A28: Mão de obra (custo da hora com encargos)
A29: Pedreiro | B29: h | C29: ='Parâmetros'!B5/'Parâmetros'!$B$15*(1+'Parâmetros'!$B$16) | D29: diária ÷ horas por dia × (1 + encargos)
A30: Servente | B30: h | C30: ='Parâmetros'!B6/'Parâmetros'!$B$15*(1+'Parâmetros'!$B$16) | D30: diária ÷ horas por dia × (1 + encargos)
A31: Eletricista | B31: h | C31: ='Parâmetros'!B7/'Parâmetros'!$B$15*(1+'Parâmetros'!$B$16) | D31: diária ÷ horas por dia × (1 + encargos)
A32: Encanador | B32: h | C32: ='Parâmetros'!B8/'Parâmetros'!$B$15*(1+'Parâmetros'!$B$16) | D32: diária ÷ horas por dia × (1 + encargos)
A33: Pintor | B33: h | C33: ='Parâmetros'!B9/'Parâmetros'!$B$15*(1+'Parâmetros'!$B$16) | D33: diária ÷ horas por dia × (1 + encargos)
A34: Carpinteiro | B34: h | C34: ='Parâmetros'!B10/'Parâmetros'!$B$15*(1+'Parâmetros'!$B$16) | D34: diária ÷ horas por dia × (1 + encargos)
A35: Azulejista | B35: h | C35: ='Parâmetros'!B11/'Parâmetros'!$B$15*(1+'Parâmetros'!$B$16) | D35: diária ÷ horas por dia × (1 + encargos)
A36: Vidraceiro | B36: h | C36: ='Parâmetros'!B12/'Parâmetros'!$B$15*(1+'Parâmetros'!$B$16) | D36: diária ÷ horas por dia × (1 + encargos)
A37: Mestre de obras | B37: h | C37: ='Parâmetros'!B13/'Parâmetros'!$B$15*(1+'Parâmetros'!$B$16) | D37: diária ÷ horas por dia × (1 + encargos)

Sheet Composições
A1: Composições de custo unitário
A2: Quanto cada serviço consome por unidade (coeficientes = exemplos de referência; ajuste com a sua experiência)
A4: Código | B4: Serviço | C4: Unid. | D4: Tipo | E4: Insumo / profissional | F4: Un. | G4: Coeficiente | H4: Preço unit. (R$) | I4: Custo (R$)
A5: S01 | B5: Alvenaria de bloco cerâmico 14 cm | C5: m² | D5: Material | E5: Bloco cerâmico 14x19x39 | F5: =IFERROR(INDEX('Insumos'!$B$5:$B$37,MATCH(E5,'Insumos'!$A$5:$A$37,0)),"?") | G5: 13.5 | H5: =IFERROR(INDEX('Insumos'!$C$5:$C$37,MATCH(E5,'Insumos'!$A$5:$A$37,0)),0) | I5: =G5*H5
A6: S01 | B6: Alvenaria de bloco cerâmico 14 cm | C6: m² | D6: Material | E6: Cimento CP-II 50 kg | F6: =IFERROR(INDEX('Insumos'!$B$5:$B$37,MATCH(E6,'Insumos'!$A$5:$A$37,0)),"?") | G6: 0.07 | H6: =IFERROR(INDEX('Insumos'!$C$5:$C$37,MATCH(E6,'Insumos'!$A$5:$A$37,0)),0) | I6: =G6*H6
A7: S01 | B7: Alvenaria de bloco cerâmico 14 cm | C7: m² | D7: Material | E7: Areia média | F7: =IFERROR(INDEX('Insumos'!$B$5:$B$37,MATCH(E7,'Insumos'!$A$5:$A$37,0)),"?") | G7: 0.012 | H7: =IFERROR(INDEX('Insumos'!$C$5:$C$37,MATCH(E7,'Insumos'!$A$5:$A$37,0)),0) | I7: =G7*H7
A8: S01 | B8: Alvenaria de bloco cerâmico 14 cm | C8: m² | D8: Material | E8: Cal hidratada 20 kg | F8: =IFERROR(INDEX('Insumos'!$B$5:$B$37,MATCH(E8,'Insumos'!$A$5:$A$37,0)),"?") | G8: 0.1 | H8: =IFERROR(INDEX('Insumos'!$C$5:$C$37,MATCH(E8,'Insumos'!$A$5:$A$37,0)),0) | I8: =G8*H8
A9: S01 | B9: Alvenaria de bloco cerâmico 14 cm | C9: m² | D9: Mão de obra | E9: Pedreiro | F9: =IFERROR(INDEX('Insumos'!$B$5:$B$37,MATCH(E9,'Insumos'!$A$5:$A$37,0)),"?") | G9: 0.9 | H9: =IFERROR(INDEX('Insumos'!$C$5:$C$37,MATCH(E9,'Insumos'!$A$5:$A$37,0)),0) | I9: =G9*H9
A10: S01 | B10: Alvenaria de bloco cerâmico 14 cm | C10: m² | D10: Mão de obra | E10: Servente | F10: =IFERROR(INDEX('Insumos'!$B$5:$B$37,MATCH(E10,'Insumos'!$A$5:$A$37,0)),"?") | G10: 0.9 | H10: =IFERROR(INDEX('Insumos'!$C$5:$C$37,MATCH(E10,'Insumos'!$A$5:$A$37,0)),0) | I10: =G10*H10
A11: S02 | B11: Chapisco em parede | C11: m² | D11: Material | E11: Cimento CP-II 50 kg | F11: =IFERROR(INDEX('Insumos'!$B$5:$B$37,MATCH(E11,'Insumos'!$A$5:$A$37,0)),"?") | G11: 0.04 | H11: =IFERROR(INDEX('Insumos'!$C$5:$C$37,MATCH(E11,'Insumos'!$A$5:$A$37,0)),0) | I11: =G11*H11
A12: S02 | B12: Chapisco em parede | C12: m² | D12: Material | E12: Areia média | F12: =IFERROR(INDEX('Insumos'!$B$5:$B$37,MATCH(E12,'Insumos'!$A$5:$A$37,0)),"?") | G12: 0.005 | H12: =IFERROR(INDEX('Insumos'!$C$5:$C$37,MATCH(E12,'Insumos'!$A$5:$A$37,0)),0) | I12: =G12*H12
A13: S02 | B13: Chapisco em parede | C13: m² | D13: Mão de obra | E13: Pedreiro | F13: =IFERROR(INDEX('Insumos'!$B$5:$B$37,MATCH(E13,'Insumos'!$A$5:$A$37,0)),"?") | G13: 0.1 | H13: =IFERROR(INDEX('Insumos'!$C$5:$C$37,MATCH(E13,'Insumos'!$A$5:$A$37,0)),0) | I13: =G13*H13
A14: S02 | B14: Chapisco em parede | C14: m² | D14: Mão de obra | E14: Servente | F14: =IFERROR(INDEX('Insumos'!$B$5:$B$37,MATCH(E14,'Insumos'!$A$5:$A$37,0)),"?") | G14: 0.1 | H14: =IFERROR(INDEX('Insumos'!$C$5:$C$37,MATCH(E14,'Insumos'!$A$5:$A$37,0)),0) | I14: =G14*H14
A15: S03 | B15: Reboco / emboço 2 cm | C15: m² | D15: Material | E15: Cimento CP-II 50 kg | F15: =IFERROR(INDEX('Insumos'!$B$5:$B$37,MATCH(E15,'Insumos'!$A$5:$A$37,0)),"?") | G15: 0.12 | H15: =IFERROR(INDEX('Insumos'!$C$5:$C$37,MATCH(E15,'Insumos'!$A$5:$A$37,0)),0) | I15: =G15*H15
A16: S03 | B16: Reboco / emboço 2 cm | C16: m² | D16: Material | E16: Cal hidratada 20 kg | F16: =IFERROR(INDEX('Insumos'!$B$5:$B$37,MATCH(E16,'Insumos'!$A$5:$A$37,0)),"?") | G16: 0.15 | H16: =IFERROR(INDEX('Insumos'!$C$5:$C$37,MATCH(E16,'Insumos'!$A$5:$A$37,0)),0) | I16: =G16*H16
... A49: S10 | B49: Troca de vidro liso 4 mm | C49: m² | D49: Mão de obra | E49: Vidraceiro | F49: =IFERROR(INDEX('Insumos'!$B$5:$B$37,MATCH(E49,'Insumos'!$A$5:$A$37,0)),"?") | G49: 0.8 | H49: =IFERROR(INDEX('Insumos'!$C$5:$C$37,MATCH(E49,'Insumos'!$A$5:$A$37,0)),0) | I49: =G49*H49

Sheet Serviços
A1: Serviços — custo e preço de venda
A2: Tudo calculado a partir das composições e do BDI
A4: Código | B4: Serviço | C4: Unid. | D4: Material (R$) | E4: Mão de obra (R$) | F4: Custo direto (R$) | G4: Preço c/ BDI (R$)
A5: S01 | B5: Alvenaria de bloco cerâmico 14 cm | C5: m² | D5: =SUMIFS('Composições'!$I$5:$I$110,'Composições'!$A$5:$A$110,A5,'Composições'!$D$5:$D$110,"Material") | E5: =SUMIFS('Composições'!$I$5:$I$110,'Composições'!$A$5:$A$110,A5,'Composições'!$D$5:$D$110,"Mão de obra") | F5: =D5+E5 | G5: =F5*(1+'Parâmetros'!$B$31)
A6: S02 | B6: Chapisco em parede | C6: m² | D6: =SUMIFS('Composições'!$I$5:$I$110,'Composições'!$A$5:$A$110,A6,'Composições'!$D$5:$D$110,"Material") | E6: =SUMIFS('Composições'!$I$5:$I$110,'Composições'!$A$5:$A$110,A6,'Composições'!$D$5:$D$110,"Mão de obra") | F6: =D6+E6 | G6: =F6*(1+'Parâmetros'!$B$31)
A7: S03 | B7: Reboco / emboço 2 cm | C7: m² | D7: =SUMIFS('Composições'!$I$5:$I$110,'Composições'!$A$5:$A$110,A7,'Composições'!$D$5:$D$110,"Material") | E7: =SUMIFS('Composições'!$I$5:$I$110,'Composições'!$A$5:$A$110,A7,'Composições'!$D$5:$D$110,"Mão de obra") | F7: =D7+E7 | G7: =F7*(1+'Parâmetros'!$B$31)
A8: S04 | B8: Contrapiso 5 cm | C8: m² | D8: =SUMIFS('Composições'!$I$5:$I$110,'Composições'!$A$5:$A$110,A8,'Composições'!$D$5:$D$110,"Material") | E8: =SUMIFS('Composições'!$I$5:$I$110,'Composições'!$A$5:$A$110,A8,'Composições'!$D$5:$D$110,"Mão de obra") | F8: =D8+E8 | G8: =F8*(1+'Parâmetros'!$B$31)
A9: S05 | B9: Piso cerâmico assentado com rejunte | C9: m² | D9: =SUMIFS('Composições'!$I$5:$I$110,'Composições'!$A$5:$A$110,A9,'Composições'!$D$5:$D$110,"Material") | E9: =SUMIFS('Composições'!$I$5:$I$110,'Composições'!$A$5:$A$110,A9,'Composições'!$D$5:$D$110,"Mão de obra") | F9: =D9+E9 | G9: =F9*(1+'Parâmetros'!$B$31)
A10: S06 | B10: Pintura acrílica 2 demãos c/ massa | C10: m² | D10: =SUMIFS('Composições'!$I$5:$I$110,'Composições'!$A$5:$A$110,A10,'Composições'!$D$5:$D$110,"Material") | E10: =SUMIFS('Composições'!$I$5:$I$110,'Composições'!$A$5:$A$110,A10,'Composições'!$D$5:$D$110,"Mão de obra") | F10: =D10+E10 | G10: =F10*(1+'Parâmetros'!$B$31)
A11: S07 | B11: Ponto de tomada (instalação completa) | C11: un | D11: =SUMIFS('Composições'!$I$5:$I$110,'Composições'!$A$5:$A$110,A11,'Composições'!$D$5:$D$110,"Material") | E11: =SUMIFS('Composições'!$I$5:$I$110,'Composições'!$A$5:$A$110,A11,'Composições'!$D$5:$D$110,"Mão de obra") | F11: =D11+E11 | G11: =F11*(1+'Parâmetros'!$B$31)
A12: S08 | B12: Troca de telha de fibrocimento | C12: m² | D12: =SUMIFS('Composições'!$I$5:$I$110,'Composições'!$A$5:$A$110,A12,'Composições'!$D$5:$D$110,"Material") | E12: =SUMIFS('Composições'!$I$5:$I$110,'Composições'!$A$5:$A$110,A12,'Composições'!$D$5:$D$110,"Mão de obra") | F12: =D12+E12 | G12: =F12*(1+'Parâmetros'!$B$31)
A13: S09 | B13: Instalação de assento sanitário | C13: un | D13: =SUMIFS('Composições'!$I$5:$I$110,'Composições'!$A$5:$A$110,A13,'Composições'!$D$5:$D$110,"Material") | E13: =SUMIFS('Composições'!$I$5:$I$110,'Composições'!$A$5:$A$110,A13,'Composições'!$D$5:$D$110,"Mão de obra") | F13: =D13+E13 | G13: =F13*(1+'Parâmetros'!$B$31)
A14: S10 | B14: Troca de vidro liso 4 mm | C14: m² | D14: =SUMIFS('Composições'!$I$5:$I$110,'Composições'!$A$5:$A$110,A14,'Composições'!$D$5:$D$110,"Material") | E14: =SUMIFS('Composições'!$I$5:$I$110,'Composições'!$A$5:$A$110,A14,'Composições'!$D$5:$D$110,"Mão de obra") | F14: =D14+E14 | G14: =F14*(1+'Parâmetros'!$B$31)
A16: Para um serviço novo: crie as linhas em "Composições" com um código novo (ex.: S11) e copie uma linha desta tabela trocando o código e o nome.

Sheet Estimativa m²
A1: Estimativa rápida por m²
A2: Para ter uma ideia do preço antes de detalhar o orçamento
A4: Item | B4: Valor | C4: Como preencher
A5: Tipo de obra | B5: Construção | C5: escolha: Construção, Reforma leve, Reforma média ou Reforma pesada
A6: Área (m²) | B6: 180 | C6: área construída ou reformada
A7: Custo de referência por m² (R$) | B7: 2200 | C7: use o CUB-SP do mês (Sinduscon-SP) para o padrão da obra — valor de EXEMPLO
A8: Fator do tipo de obra | B8: =IF(B5="Construção",1,IF(B5="Reforma leve",0.35,IF(B5="Reforma média",0.6,IF(B5="Reforma pesada",0.85,1)))) | C8: automático pela escolha acima
A9: Ajuste do padrão (%) | B9: 0 | C9: ex.: +10% para acabamento melhor, −10% para mais simples
A10: Custo estimado da obra | B10: =B6*B7*B8*(1+B9) | C10: área × custo/m² × fator × (1 + ajuste)
A11: BDI | B11: ='Parâmetros'!$B$31 | C11: vem da aba Parâmetros
A12: PREÇO ESTIMADO DE VENDA | B12: =B10*(1+B11) | C12: custo estimado × (1 + BDI)
A13: Preço por m² | B13: =IF(B6=0,0,B12/B6)
A15: Fatores de reforma (0,35 / 0,60 / 0,85) são estimativas de partida — ajuste na fórmula de B8 conforme a sua experiência.
